azure_recommendations_1/__init__.py
azure_recommendations_1/recommendation/__init__.py
azure_recommendations_1/recommendation/advisor_recommendations.py
azure_recommendations_1/recommendation/network_recommendations.py
azure_recommendations_1/recommendation/utils.py
azure_recommendations_1/recommendation/vm_recommendations.py
azure_recommendations_1-0.1.2.dist-info/LICENCE
azure_recommendations_1-0.1.2.dist-info/METADATA
azure_recommendations_1-0.1.2.dist-info/WHEEL
azure_recommendations_1-0.1.2.dist-info/top_level.txt
azure_recommendations_1-0.1.2.dist-info/RECORD
